auth_api/__init__.py
auth_api/controller.py
auth_api/models.py
auth_api/service.py
auth_api_intra-0.1.1.dist-info/METADATA
auth_api_intra-0.1.1.dist-info/WHEEL
auth_api_intra-0.1.1.dist-info/top_level.txt
auth_api_intra-0.1.1.dist-info/RECORD
