Metadata-Version: 2.4
Name: auth_api_intra
Version: 0.1.1
Summary: Reusable Auth API logic component
Home-page: https://github.com/Intra-preneur/monorepo
Author: Sajjad
Author-email: syedsajjadali258@gmail.com
Classifier: Programming Language :: Python :: 3
Classifier: License :: OSI Approved :: MIT License
Requires-Python: >=3.9
Requires-Dist: fastapi
Requires-Dist: python-jose[cryptography]
Dynamic: author
Dynamic: author-email
Dynamic: classifier
Dynamic: description
Dynamic: description-content-type
Dynamic: home-page
Dynamic: requires-dist
Dynamic: requires-python
Dynamic: summary
